pplpy.libs/libppl-c6b79794.so.14.0.0
pplpy.libs/libgmpxx-0a39215a.so.4.7.0
pplpy.libs/libgmp-1367b825.so.10.5.0
pplpy-0.8.10rc2.dist-info/RECORD
pplpy-0.8.10rc2.dist-info/METADATA
pplpy-0.8.10rc2.dist-info/WHEEL
pplpy-0.8.10rc2.dist-info/top_level.txt
pplpy-0.8.10rc2.dist-info/LICENSE.txt
ppl/constraint.pxd
ppl/__init__.py
ppl/ppl_shim.hh
ppl/linear_algebra.pxd
ppl/polyhedron.cpython-39-x86_64-linux-gnu.so
ppl/bit_arrays.pxd
ppl/bit_arrays.cpython-39-x86_64-linux-gnu.so
ppl/ppl_decl.pxd
ppl/mip_problem.pxd
ppl/polyhedron.pxd
ppl/congruence.pxd
ppl/congruence.cpython-39-x86_64-linux-gnu.so
ppl/mip_problem.cpython-39-x86_64-linux-gnu.so
ppl/generator.cpython-39-x86_64-linux-gnu.so
ppl/linear_algebra.cpython-39-x86_64-linux-gnu.so
ppl/constraint.cpython-39-x86_64-linux-gnu.so
ppl/generator.pxd
