Metadata-Version: 2.1
Name: pplpy
Version: 0.8.10rc2
Summary: Python PPL wrapper
Author-email: Vincent Delecroix <vincent.delecroix@labri.fr>
License: GPL v3
Project-URL: Homepage, https://github.com/sagemath/pplpy
Project-URL: Download, https://pypi.org/project/pplpy/#files
Keywords: polyhedron,polytope,convex,mathematics,ppl,milp,linear-programming
Platform: any
Classifier: License :: OSI Approved :: GNU General Public License v3 (GPLv3)
Classifier: Programming Language :: C++
Classifier: Programming Language :: Python
Classifier: Development Status :: 5 - Production/Stable
Classifier: Operating System :: Unix
Classifier: Intended Audience :: Science/Research
Classifier: Programming Language :: Python :: 3.8
Classifier: Programming Language :: Python :: 3.9
Classifier: Programming Language :: Python :: 3.10
Classifier: Programming Language :: Python :: 3.11
Classifier: Programming Language :: Python :: 3.12
License-File: LICENSE.txt
Requires-Dist: cysignals
Requires-Dist: gmpy2 >=2.1.0b1
Provides-Extra: doc
Requires-Dist: sphinx ; extra == 'doc'
